{
  "name": "3D City",
  "website": "https://3dcity.life/",
  "source_code": "https://github.com/3dcitymetaverse/citymetaverse",
  "short_description": "3D City is a decentralized and tokenized platform that offers gamers all over the world a Triple-A gaming experience. The first Play-2-Earn release will be 3D City Metaverse.",
  "explorer": "https://scanbrc.com/token/0x5feDA75eaB27814Cba0694C9711F7d4abEa5b0b5/token-transfers",
  "research": "",
  "socials": [
    {
      "name": "Twitter",
      "url": "https://twitter.com/3dcitymetaverse"
    },
    {
      "name": "Telegram",
      "url": "https://t.me/citygamecommunity"
    }
  ]
}
